clodius/__init__.py
clodius/_tsv_to_mrmatrix.py
clodius/array.py
clodius/chromosomes.py
clodius/db_tiles.py
clodius/describe_dataset.py
clodius/fpark.py
clodius/hdf_tiles.py
clodius/higlass_getter.py
clodius/multivec.py
clodius/save_tiles.py
clodius/cli/__init__.py
clodius/cli/aggregate.py
clodius/cli/convert.py
clodius/cli/utils.py
clodius/models/tileset_info.py
clodius/tiles/__init__.py
clodius/tiles/bam.py
clodius/tiles/bed2ddb.py
clodius/tiles/bedarcsdb.py
clodius/tiles/beddb.py
clodius/tiles/bedfile.py
clodius/tiles/bigbed.py
clodius/tiles/bigwig.py
clodius/tiles/chromsizes.py
clodius/tiles/cooler.py
clodius/tiles/density.py
clodius/tiles/fasta.py
clodius/tiles/files.py
clodius/tiles/format.py
clodius/tiles/geo.py
clodius/tiles/hitile.py
clodius/tiles/imtiles.py
clodius/tiles/mrmatrix.py
clodius/tiles/multivec.py
clodius/tiles/nplabels.py
clodius/tiles/npmatrix.py
clodius/tiles/npvector.py
clodius/tiles/points.py
clodius/tiles/tabix.py
clodius/tiles/time_interval.py
clodius/tiles/utils.py
clodius-0.20.4.dist-info/METADATA
clodius-0.20.4.dist-info/WHEEL
clodius-0.20.4.dist-info/entry_points.txt
clodius-0.20.4.dist-info/licenses/LICENSE
clodius-0.20.4.dist-info/RECORD
