Metadata-Version: 2.4
Name: clodius
Version: 0.20.4
Summary: Tile generation for big data
Project-URL: homepage, https://github.com/higlass/clodius
Author-email: Peter Kerpedjiev <pkerpedjiev@gmail.com>
License: MIT
License-File: LICENSE
Requires-Dist: click>=7
Requires-Dist: cooler>0.9.0
Requires-Dist: dask
Requires-Dist: h5py
Requires-Dist: negspy
Requires-Dist: numpy
Requires-Dist: pandas>=1.0
Requires-Dist: pybbi>=0.2.0
Requires-Dist: pydantic
Requires-Dist: pyfaidx
Requires-Dist: pysam
Requires-Dist: requests
Requires-Dist: slugid
Requires-Dist: smart-open
Requires-Dist: sortedcontainers
Requires-Dist: tqdm
Provides-Extra: dev
Requires-Dist: autopep8; extra == 'dev'
Requires-Dist: bumpversion; extra == 'dev'
Requires-Dist: flake8; extra == 'dev'
Requires-Dist: pytest; extra == 'dev'
Requires-Dist: pytest-cov; extra == 'dev'
